{
    "domain": "Construção",
    "service": "financeiro",
    "menu":{
        "id" : "mydomain/myservice/sample-management",
        "label":"Construção",
        "labelI18n":"platform.backend.my_domain_sample_management",
        "children":[
            {
                "id" : "mydomain/myservice/level01",
                "label":"Financeiro",
                "labelI18n":"platform.backend.my_domain_my_service_level1",
                "auth":{
                    "resource":"res://senior.com.br/security/usermanager/usuario",
                    "permission":"Consultar"
                },
                "children":[
                    {
                        "id" : "mydomain/myservice/level02",
                        "label":"Carteira de recebíveis",
                        "labelI18n":"platform.backend.my_domain_my_service_level2",
                        "auth":{
                            "resource":"res://senior.com.br/security/usermanager/usuario",
                            "permission":"Consultar"
                        }
                    },
                    {
                        "label":"Multi-nível",
                        "children":[
                            {
                                "label":"Level 1",
                                "children":[
                                    {
                                        "label":"Level 2",
                                        "children":[
                                            {
                                                "label":"Level 3",
                                                "children":[
                                                    {
                                                        "label":"Congrats! You've made it"
                                                    }
                                                ]
                                            }
                                        ]
                                    }
                                ]
                            }
                        ]
                    }
                ]
            }
        ]
    }
}